snakemake_executor_plugin_kueue/__init__.py
snakemake_executor_plugin_kueue/custom_resource.py
snakemake_executor_plugin_kueue/executor.py
snakemake_executor_plugin_kueue/utils.py
snakemake_executor_plugin_kueue-0.1.0.dist-info/LICENSE
snakemake_executor_plugin_kueue-0.1.0.dist-info/METADATA
snakemake_executor_plugin_kueue-0.1.0.dist-info/WHEEL
snakemake_executor_plugin_kueue-0.1.0.dist-info/RECORD
