Metadata-Version: 2.1
Name: snakemake-executor-plugin-kueue
Version: 0.1.0
Summary: 
Author: vsoch
Author-email: vsoch@users.noreply.github.com
Requires-Python: >=3.11,<4.0
Classifier: Programming Language :: Python :: 3
Classifier: Programming Language :: Python :: 3.11
Classifier: Programming Language :: Python :: 3.12
Requires-Dist: kubernetes (>=28.1.0,<29.0.0)
Requires-Dist: oras (>=0.1.25,<0.2.0)
Requires-Dist: portforward (>=0.6.0,<0.7.0)
Requires-Dist: requests (>=2.31.0,<3.0.0)
